{
    "Background":"./assets/img/bg_img_2.png",
    "yOffset": 20,
    "Enemies":[
        {
            "ID":"en2-1",
            "name":"辐光",
            "type":"boss",
            "HP":150,
            "maxHP":200,
            "SP":100,
            "SPHeal":100,
            "maxSP":100,
            "cards":[
                {
                    "ID":"2-1-1",
                    "title":"瘟疫盛开",
                    "description":"",
                    "gate":"or",
                    "type":"True",
                    "level":4,
                    "effects":[

                    ],
                    "imgLocation":"./assets/card/2-1-1.png"
                },
                {
                    "ID":"2-1-2",
                    "title":"贯穿长剑",
                    "description":"",
                    "gate":"or",
                    "type":"True",
                    "level":4,
                    "effects":[

                    ],
                    "imgLocation":"./assets/card/2-1-2.png"
                },
                {
                    "ID":"2-1-3",
                    "title":"瘟疫播种",
                    "description":"",
                    "gate":"and",
                    "type":"False",
                    "level":6,
                    "effects":[

                    ],
                    "imgLocation":"./assets/card/2-1-3.png"
                },
                {
                    "ID":"2-1-4",
                    "title":"瘟疫绽放",
                    "description":"",
                    "gate":"and",
                    "type":"True",
                    "level":4,
                    "effects":[

                    ],
                    "imgLocation":"./assets/card/2-1-4.png"
                },
                {
                    "ID":"2-1-5",
                    "title":"光之梦境",
                    "description":"",
                    "gate":"or",
                    "type":"True",
                    "level":4,
                    "effects":[

                    ],
                    "imgLocation":"./assets/card/2-1-5.png"
                },
                {
                    "ID":"2-1-6",
                    "title":"尖刺陷阱",
                    "description":"",
                    "gate":"or",
                    "type":"False",
                    "level":6,
                    "effects":[

                    ],
                    "imgLocation":"./assets/card/2-1-6.png"
                },
                {
                    "ID":"2-1-7",
                    "title":"光柱发射",
                    "description":"",
                    "gate":"and",
                    "type":"True",
                    "level":4,
                    "effects":[

                    ],
                    "imgLocation":"./assets/card/2-1-7.png"
                },
                {
                    "ID":"2-1-8",
                    "title":"不绝瘟疫",
                    "description":"",
                    "gate":"and",
                    "type":"True",
                    "level":4,
                    "effects":[

                    ],
                    "imgLocation":"./assets/card/2-1-8.png"
                },
                {
                    "ID":"2-1-9",
                    "title":"我！不！会！被！遗！忘！",
                    "description":"",
                    "gate":"and",
                    "type":"True",
                    "level":7,
                    "effects":[

                    ],
                    "imgLocation":"./assets/card/2-1-9.png"
                },
                {
                    "ID":"2-1-10",
                    "title":"黎！明！必！将！到！来！",
                    "description":"",
                    "gate":"and",
                    "type":"False",
                    "level":10,
                    "effects":[

                    ],
                    "imgLocation":"./assets/card/2-1-10.png"
                },
                {
                    "ID":"2-1-11",
                    "title":"战胜黑暗",
                    "description":"本卡无法被操作。本卡不计入拼点。受到伤害时，伤害减少本卡等级，若伤害因此变为零，下回合固定使用特殊强卡。",
                    "gate":"None",
                    "type":"False",
                    "level":6,
                    "effects":[
                        "selectProhibit",
                        "defence",
                        "hasCounterAttack"
                    ],
                    "imgLocation":"./assets/card/2-1-11.png"
                },
                {
                    "ID":"2-1-12",
                    "title":"天将拂晓",
                    "description":"本卡无法被操作。本卡不计入拼点。受到伤害时，伤害减少本卡等级，若伤害因此变为零，下回合固定使用特殊强卡。",
                    "gate":"None",
                    "type":"True",
                    "level":6,
                    "effects":[
                        "selectProhibit",
                        "defence",
                        "hasCounterAttack"
                    ],
                    "imgLocation":"./assets/card/2-1-12.png"
                },
                {
                    "ID":"2-1-13",
                    "title":"以牙还牙",
                    "description":"本卡无法被操作。",
                    "gate":"None",
                    "type":"False",
                    "level":16,
                    "effects":[
                        "selectProhibit"
                    ],
                    "imgLocation":"./assets/card/2-1-13.png"
                },
                {
                    "ID":"2-1-14",
                    "title":"以眼还眼",
                    "description":"本卡无法被操作。",
                    "gate":"None",
                    "type":"True",
                    "level":16,
                    "effects":[
                        "selectProhibit"
                    ],
                    "imgLocation":"./assets/card/2-1-14.png"
                },
                {
                    "ID":"2-1-15",
                    "title":"不灭光芒",
                    "description":"若本卡未被操作，拼点结束后回复 25 点生命。",
                    "gate":"and",
                    "type":"True",
                    "level":0,
                    "effects":[
                        "HPheal_25_fragile"
                    ],
                    "imgLocation":"./assets/card/2-1-15.png"
                }
            ],
            "strategy":[
                ["2-1-1", "2-1-2", "2-1-3", "2-1-4", "2-1-5", "2-1-6"],
                ["2-1-1", "2-1-2", "2-1-3", "2-1-4", "2-1-5", "2-1-7"],
                ["2-1-1", "2-1-2", "2-1-3", "2-1-4", "2-1-5", "2-1-8"],
                ["2-1-1", "2-1-2", "2-1-3", "2-1-4", "2-1-6", "2-1-7"],
                ["2-1-1", "2-1-2", "2-1-3", "2-1-4", "2-1-6", "2-1-8"],
                ["2-1-1", "2-1-2", "2-1-3", "2-1-4", "2-1-7", "2-1-8"],
                ["2-1-1", "2-1-2", "2-1-3", "2-1-5", "2-1-6", "2-1-7"],
                ["2-1-1", "2-1-2", "2-1-3", "2-1-5", "2-1-6", "2-1-8"],
                ["2-1-1", "2-1-2", "2-1-3", "2-1-5", "2-1-7", "2-1-8"],
                ["2-1-1", "2-1-2", "2-1-3", "2-1-6", "2-1-7", "2-1-8"],
                ["2-1-1", "2-1-2", "2-1-4", "2-1-5", "2-1-6", "2-1-7"],
                ["2-1-1", "2-1-2", "2-1-4", "2-1-5", "2-1-6", "2-1-8"],
                ["2-1-1", "2-1-2", "2-1-4", "2-1-5", "2-1-7", "2-1-8"],
                ["2-1-1", "2-1-2", "2-1-4", "2-1-6", "2-1-7", "2-1-8"],
                ["2-1-1", "2-1-2", "2-1-5", "2-1-6", "2-1-7", "2-1-8"],
                ["2-1-1", "2-1-3", "2-1-4", "2-1-5", "2-1-6", "2-1-7"],
                ["2-1-1", "2-1-3", "2-1-4", "2-1-5", "2-1-6", "2-1-8"],
                ["2-1-1", "2-1-3", "2-1-4", "2-1-5", "2-1-7", "2-1-8"],
                ["2-1-1", "2-1-3", "2-1-4", "2-1-6", "2-1-7", "2-1-8"],
                ["2-1-1", "2-1-3", "2-1-5", "2-1-6", "2-1-7", "2-1-8"],
                ["2-1-1", "2-1-4", "2-1-5", "2-1-6", "2-1-7", "2-1-8"],
                ["2-1-2", "2-1-3", "2-1-4", "2-1-5", "2-1-6", "2-1-7"],
                ["2-1-2", "2-1-3", "2-1-4", "2-1-5", "2-1-6", "2-1-8"],
                ["2-1-2", "2-1-3", "2-1-4", "2-1-5", "2-1-7", "2-1-8"],
                ["2-1-2", "2-1-3", "2-1-4", "2-1-6", "2-1-7", "2-1-8"],
                ["2-1-2", "2-1-3", "2-1-5", "2-1-6", "2-1-7", "2-1-8"],
                ["2-1-2", "2-1-4", "2-1-5", "2-1-6", "2-1-7", "2-1-8"],
                ["2-1-3", "2-1-4", "2-1-5", "2-1-6", "2-1-7", "2-1-8"],
                ["2-1-3", "2-1-6", "2-1-9", "2-1-10", "2-1-15"],
                ["2-1-3", "2-1-6", "2-1-9", "2-1-10"],
                ["2-1-3", "2-1-6", "2-1-9", "2-1-10"],
                ["2-1-1", "2-1-4", "2-1-8", "2-1-9", "2-1-10", "2-1-15"],
                ["2-1-1", "2-1-4", "2-1-8", "2-1-9", "2-1-10"],
                ["2-1-1", "2-1-4", "2-1-8", "2-1-9", "2-1-10"],
                ["2-1-5", "2-1-6", "2-1-9", "2-1-10", "2-1-15"],
                ["2-1-5", "2-1-6", "2-1-9", "2-1-10"],
                ["2-1-5", "2-1-6", "2-1-9", "2-1-10"],
                ["2-1-3", "2-1-7", "2-1-9", "2-1-10", "2-1-15"],
                ["2-1-3", "2-1-7", "2-1-9", "2-1-10"],
                ["2-1-3", "2-1-7", "2-1-9", "2-1-10"],
                ["2-1-1", "2-1-2", "2-1-3", "2-1-6", "2-1-11"],
                ["2-1-1", "2-1-2", "2-1-3", "2-1-6", "2-1-11"],
                ["2-1-1", "2-1-2", "2-1-3", "2-1-6", "2-1-12"],
                ["2-1-1", "2-1-2", "2-1-3", "2-1-6", "2-1-12"],
                ["2-1-6", "2-1-8", "2-1-11", "2-1-12"],
                ["2-1-11", "2-1-12", "2-1-15"]
            ],
            "specialStrategy": {
                "counterAttack": [
                    "2-1-13",
                    "2-1-14",
                    "2-1-15"
                ]
            },
            "imgLocation":"./assets/char/en-2-1",
            "posXoffset":-100,
            "posYoffset":-40,
            "imgSize": [350, 350],
            "imgDashSize": [350, 350],
            "imgAttackSize": [300, 370]
        }
    ]
}